pyqtspecgram/__init__.py
pyqtspecgram/pyqtspecgram.py
pyqtspecgram-0.1.0.dist-info/LICENSE
pyqtspecgram-0.1.0.dist-info/METADATA
pyqtspecgram-0.1.0.dist-info/WHEEL
pyqtspecgram-0.1.0.dist-info/top_level.txt
pyqtspecgram-0.1.0.dist-info/RECORD
