Metadata-Version: 2.1
Name: pyqtspecgram
Version: 0.1.0
Summary: Python spectogram plotted using pyqtgraph.
Home-page: https://github.com/epeters13/pyqtspecgram
Author: Edwin G. W. Peters
Author-email: edwin.g.w.peters@gmail.com
License: GPL3
Keywords: spectrogram specgram waterfall pyqtgraph
Platform: UNKNOWN
Classifier: Development Status :: 4 - Beta
Classifier: Intended Audience :: Developers
Classifier: Topic :: Software Development :: Libraries
Classifier: License :: OSI Approved :: GNU General Public License v3 or later (GPLv3+)
Classifier: Programming Language :: Python :: 3
Requires-Python: >=3.6
License-File: LICENSE
Requires-Dist: scipy
Requires-Dist: pyqtgraph
